cdk_cloudfront_plus/__init__.py
cdk_cloudfront_plus/py.typed
cdk_cloudfront_plus/_jsii/__init__.py
cdk_cloudfront_plus/_jsii/cdk-cloudfront-plus@0.3.172.jsii.tgz
cdk_cloudfront_plus-0.3.172.dist-info/LICENSE
cdk_cloudfront_plus-0.3.172.dist-info/METADATA
cdk_cloudfront_plus-0.3.172.dist-info/WHEEL
cdk_cloudfront_plus-0.3.172.dist-info/top_level.txt
cdk_cloudfront_plus-0.3.172.dist-info/RECORD
