Metadata-Version: 2.1
Name: cdk-cloudfront-plus
Version: 0.3.172
Summary: CDK construct library for CloudFront Extensions
Home-page: https://github.com/pahud/cdk-cloudfront-plus.git
Author: Pahud Hsieh<pahudnet@gmail.com>
License: Apache-2.0
Project-URL: Source, https://github.com/pahud/cdk-cloudfront-plus.git
Platform: UNKNOWN
Classifier: Intended Audience :: Developers
Classifier: Operating System :: OS Independent
Classifier: Programming Language :: JavaScript
Classifier: Programming Language :: Python :: 3 :: Only
Classifier: Programming Language :: Python :: 3.6
Classifier: Programming Language :: Python :: 3.7
Classifier: Programming Language :: Python :: 3.8
Classifier: Programming Language :: Python :: 3.9
Classifier: Typing :: Typed
Classifier: Development Status :: 5 - Production/Stable
Classifier: License :: OSI Approved
Requires-Python: >=3.6
License-File: LICENSE
Requires-Dist: aws-cdk.aws-apigatewayv2-integrations (<2.0.0,>=1.73.0)
Requires-Dist: aws-cdk.aws-apigatewayv2 (<2.0.0,>=1.73.0)
Requires-Dist: aws-cdk.aws-cloudfront-origins (<2.0.0,>=1.73.0)
Requires-Dist: aws-cdk.aws-cloudfront (<2.0.0,>=1.73.0)
Requires-Dist: aws-cdk.aws-iam (<2.0.0,>=1.73.0)
Requires-Dist: aws-cdk.aws-kinesisfirehose (<2.0.0,>=1.73.0)
Requires-Dist: aws-cdk.aws-lambda-nodejs (<2.0.0,>=1.73.0)
Requires-Dist: aws-cdk.aws-lambda (<2.0.0,>=1.73.0)
Requires-Dist: aws-cdk.aws-s3-deployment (<2.0.0,>=1.73.0)
Requires-Dist: aws-cdk.aws-s3 (<2.0.0,>=1.73.0)
Requires-Dist: aws-cdk.aws-sam (<2.0.0,>=1.73.0)
Requires-Dist: aws-cdk.core (<2.0.0,>=1.73.0)
Requires-Dist: constructs (<4.0.0,>=3.2.27)
Requires-Dist: jsii (<2.0.0,>=1.47.0)
Requires-Dist: publication (>=0.0.3)
